serf_client2/__init__.py
serf_client2/client.py
serf_client2/connection.py
serf_client2-1.0.0.dist-info/DESCRIPTION.rst
serf_client2-1.0.0.dist-info/METADATA
serf_client2-1.0.0.dist-info/RECORD
serf_client2-1.0.0.dist-info/WHEEL
serf_client2-1.0.0.dist-info/metadata.json
serf_client2-1.0.0.dist-info/top_level.txt
